open_channel/constants.py
open_channel/rectangular_section.py
open_channel/section.py
open_channel-0.0.0.dist-info/LICENSE
open_channel-0.0.0.dist-info/METADATA
open_channel-0.0.0.dist-info/WHEEL
open_channel-0.0.0.dist-info/RECORD
