Metadata-Version: 2.1
Name: open-channel
Version: 0.0.0
Summary: 
Home-page: https://www.onf.fr/
License: GPL-3.0-or-later
Author: ONF-RTM
Maintainer: Clément Roussel
Maintainer-email: clement.roussel@onf.fr
Requires-Python: >=3.9,<4.0
Classifier: License :: OSI Approved :: GNU General Public License v3 or later (GPLv3+)
Classifier: Programming Language :: Python :: 3
Classifier: Programming Language :: Python :: 3.9
Classifier: Programming Language :: Python :: 3.10
Classifier: Programming Language :: Python :: 3.11
Requires-Dist: matplotlib (>=3.6.2,<4.0.0)
Requires-Dist: numpy (>=1.24.1,<2.0.0)
Requires-Dist: pandas (>=1.5.2,<2.0.0)
Requires-Dist: scipy (>=1.9.3,<2.0.0)
Project-URL: Documentation, https://open-channel.readthedocs.io/fr/latest/
Project-URL: Repository, https://github.com/clementroussel/open-channel
